beamdust/__init__.py
beamdust/beamdust.py
beamdust/config.py
beamdust/exceptions.py
beamdust/main.py
beamdust_sdk-1.0.2.dist-info/LICENSE
beamdust_sdk-1.0.2.dist-info/METADATA
beamdust_sdk-1.0.2.dist-info/WHEEL
beamdust_sdk-1.0.2.dist-info/top_level.txt
beamdust_sdk-1.0.2.dist-info/RECORD
