Metadata-Version: 2.1
Name: beamdust-sdk
Version: 1.0.2
Summary: A Python SDK for interacting with Beamdust API
Home-page: https://github.com/Beamdust/beamdust-package
Author: Lautaro Torchia
Author-email: ltorchia@novakorp.io
License: UNKNOWN
Project-URL: Bug Tracker, https://github.com/Beamdust/beamdust-package/issues
Platform: UNKNOWN
Classifier: Programming Language :: Python :: 3
Classifier: License :: OSI Approved :: MIT License
Classifier: Operating System :: OS Independent
Requires-Python: >=3.6
Requires-Dist: jinja2
Requires-Dist: requests
Requires-Dist: urllib3
